README.md
flantastic/__init__.py
flantastic/admin.py
flantastic/api/__init__.py
flantastic/api/serializers.py
flantastic/api/viewsets.py
flantastic/apps.py
flantastic/data/__init__.py
flantastic/data/bakeries_downloader.py
flantastic/data/bakeries_importer.py
flantastic/data/definitions.py
flantastic/definitions.py
flantastic/forms.py
flantastic/management/__init__.py
flantastic/management/commands/import_initial_data.py
flantastic/migrations/0001_initial.py
flantastic/migrations/0002_float_global_note.py
flantastic/migrations/__init__.py
flantastic/models.py
flantastic/serializers.py
flantastic/signals.py
flantastic/static/flantastic/css/headerbar.css
flantastic/static/flantastic/css/login.css
flantastic/static/flantastic/css/mapstyle.css
flantastic/static/flantastic/css/sidemenu.css
flantastic/static/flantastic/css/signup.css
flantastic/static/flantastic/css/style.css
flantastic/static/flantastic/icons/bad_bakery.png
flantastic/static/flantastic/icons/good_bakery.png
flantastic/static/flantastic/icons/medium_bakery.png
flantastic/static/flantastic/icons/unnoted_bakery.png
flantastic/static/flantastic/images/icons/icon-128x128.png
flantastic/static/flantastic/images/icons/icon-144x144.png
flantastic/static/flantastic/images/icons/icon-152x152.png
flantastic/static/flantastic/images/icons/icon-192x192.png
flantastic/static/flantastic/images/icons/icon-384x384.png
flantastic/static/flantastic/images/icons/icon-512x512.png
flantastic/static/flantastic/images/icons/icon-72x72.png
flantastic/static/flantastic/images/icons/icon-96x96.png
flantastic/static/flantastic/js/mainjs.js
flantastic/static/flantastic/js/map_init.js
flantastic/static/flantastic/js/sidemenu.js
flantastic/templates/flantastic/base.html
flantastic/templates/flantastic/headerbar.html
flantastic/templates/flantastic/login.html
flantastic/templates/flantastic/logout.html
flantastic/templates/flantastic/maplayer.html
flantastic/templates/flantastic/sidemenu.html
django_flantastic-0.4.0.dist-info/LICENSE
django_flantastic-0.4.0.dist-info/WHEEL
django_flantastic-0.4.0.dist-info/METADATA
django_flantastic-0.4.0.dist-info/RECORD
